liwcanalysis/__init__.py
liwcanalysis/liwcanalysis.py
liwc_analysis-1.2.4.dist-info/LICENSE
liwc_analysis-1.2.4.dist-info/METADATA
liwc_analysis-1.2.4.dist-info/WHEEL
liwc_analysis-1.2.4.dist-info/top_level.txt
liwc_analysis-1.2.4.dist-info/RECORD
