Metadata-Version: 2.1
Name: liwc-analysis
Version: 1.2.4
Summary: Driver for LIWC2015 analysis. LIWC2015 dictionary not included.
Home-page: https://github.com/EricWiener/liwc-analysis
Author: Eric Wiener
Author-email: ericwiener3@gmail.com
License: UNKNOWN
Platform: UNKNOWN
Classifier: Programming Language :: Python :: 3
Classifier: License :: OSI Approved :: MIT License
Classifier: Operating System :: OS Independent
Requires-Dist: pandas
